<?xml version="1.0" encoding="UTF-8" standalone="no"?>
<event category="CREATE" id="0">
  <actions>
    <action id="603" library="1">
      <!--action name: Code-->
      <kind>CODE</kind>
      <allowRelative>false</allowRelative>
      <question>false</question>
      <canApplyTo>true</canApplyTo>
      <actionType>CODE</actionType>
      <functionName/>
      <relative>false</relative>
      <not>false</not>
      <appliesTo>.self</appliesTo>
      <arguments>
        <argument kind="STRING">dialogMsg = noone;
alpha = 0;
fadeOut = false;
alarm[0] = 100 / global.delta_factor;

color = -1;
switch(global.myself.team) {
    case TEAM_RED:
        color = c_red;
        break;
    case TEAM_BLUE:
        color = c_blue;
        break;
    default:
        color = c_white;
}
</argument>
      </arguments>
    </action>
  </actions>
</event>
